reddit_radio/__init__.py
reddit_radio/cli.py
reddit_radio/config.py
reddit_radio/database.py
reddit_radio/helpers.py
reddit_radio/logging.py
reddit_radio/mpv.py
reddit_radio/reddit.py
reddit_radio/templates/config.sample.ini
reddit_radio/youtube.py
reddit_radio-0.0.2.dist-info/entry_points.txt
reddit_radio-0.0.2.dist-info/LICENSE
reddit_radio-0.0.2.dist-info/WHEEL
reddit_radio-0.0.2.dist-info/METADATA
reddit_radio-0.0.2.dist-info/RECORD
