Metadata-Version: 2.1
Name: reddit-radio
Version: 0.0.2
Summary: Listen to music shared on reddit from your command line
Home-page: https://github.com/martini97/reddit_radio
License: AGPL-3.0-or-later
Keywords: reddit,radio,music,cli
Author: martini97
Author-email: martini97@protonmail.ch
Maintainer: martini97
Maintainer-email: martini97@protonmail.ch
Requires-Python: >=3.8,<4.0
Classifier: License :: OSI Approved :: GNU Affero General Public License v3 or later (AGPLv3+)
Classifier: Programming Language :: Python :: 3
Classifier: Programming Language :: Python :: 3.8
Classifier: Programming Language :: Python :: 3.9
Requires-Dist: click (>=7.1.2,<8.0.0)
Requires-Dist: loguru (>=0.5.3,<0.6.0)
Requires-Dist: peewee (>=3.14.4,<4.0.0)
Requires-Dist: praw (>=7.2.0,<8.0.0)
Requires-Dist: python-mpv-jsonipc (>=1.1.13,<2.0.0)
Requires-Dist: xdg (>=5.0.1,<6.0.0)
Project-URL: Repository, https://github.com/martini97/reddit_radio
